README.rst
setup.py
BeanCommonUtils.egg-info/PKG-INFO
BeanCommonUtils.egg-info/SOURCES.txt
BeanCommonUtils.egg-info/dependency_links.txt
BeanCommonUtils.egg-info/requires.txt
BeanCommonUtils.egg-info/top_level.txt
BeanCommonUtils.egg-info/zip-safe
common_utils/__init__.py
common_utils/date_utils.py
common_utils/file_utils.py
common_utils/htmlTestRunner.py
common_utils/http_operate.py
common_utils/log_decorator.py
common_utils/mysql_operate.py
common_utils/mysql_pool.py
common_utils/new_log.py
common_utils/print_method_name.py
common_utils/rand_utils.py
common_utils/trace_logger.py