Metadata-Version: 1.1
Name: BeanCommonUtils
Version: 1.1.7
Summary: A Python library for common methods.
Home-page: https://github.com/beansKingdom/CommonUtils
Author: Hly
Author-email: hlyaction@gmail.com
License: MIT
Platform: UNKNOWN
Classifier: Programming Language :: Python :: 3
Classifier: License :: OSI Approved :: MIT License
Classifier: Operating System :: OS Independent
